LAB00/src/accumulator.v
module accumulator (
    input wire clk,
    input wire rst,
    input wire start,
    input wire [3:0] x,
    output reg [5:0] acc,
    output reg done
);

    // Definición de Estados de la FSM
    localparam S0_IDLE = 2'b00;
    localparam S1_LOAD = 2'b01;
    localparam S2_ADD  = 2'b10;
    localparam S3_DONE = 2'b11;

    reg [1:0] state, next_state;
    reg [1:0] cnt; // Contador interno de ciclos (0 a 3)

    // 1. Registro de Estado (Lógica Secuencial)
    always @(posedge clk or posedge rst) begin
        if (rst) begin
            state <= S0_IDLE;
        end else begin
            state <= next_state;
        end
    end

    // 2. Lógica del Próximo Estado (Lógica Combinacional)
    always @(*) begin
        case (state)
            S0_IDLE: next_state = (start) ? S1_LOAD : S0_IDLE;
            S1_LOAD: next_state = S2_ADD;
            S2_ADD:  next_state = (cnt == 2'd3) ? S3_DONE : S2_ADD;
            S3_DONE: next_state = S0_IDLE;
            default: next_state = S0_IDLE;
        endcase
    end

    // 3. Datapath y Salidas (Lógica Secuencial y de Control)
    always @(posedge clk or posedge rst) begin
        if (rst) begin
            acc  <= 6'd0;
            cnt  <= 2'd0;
            done <= 1'b0;
        end else begin
            case (state)
                S0_IDLE: begin
                    done <= 1'b0;
                end
                S1_LOAD: begin
                    acc  <= 6'd0;
                    cnt  <= 2'd0;
                    done <= 1'b0;
                end
                S2_ADD: begin
                    acc  <= acc + x;
                    cnt  <= cnt + 2'd1;
                    done <= 1'b0;
                end
                S3_DONE: begin
                    done <= 1'b1;
                end
            endcase
        end
    end

endmodule

LAB00/src/tb_accumulator.v
`timescale 1ns/1ps

module tb_accumulator;

    // Entradas del testbench (reg)
    reg clk;
    reg rst;
    reg start;
    reg [3:0] x;

    // Salidas del módulo (wire)
    wire [5:0] acc;
    wire done;

    // Instancia del módulo a probar (UUT)
    accumulator uut (
        .clk(clk),
        .rst(rst),
        .start(start),
        .x(x),
        .acc(acc),
        .done(done)
    );

    // Generación del reloj (Periodo = 10ns -> 100MHz)
    always #5 clk = ~clk;

    initial begin
        // Configuración para guardar las ondas para GTKWave
        $dumpfile("accumulator.vcd");
        $dumpvars(0, tb_accumulator);

        // Inicialización de señales
        clk = 0;
        rst = 1;
        start = 0;
        x = 4'd0;

        // Reset inicial
        #15;
        rst = 0;
        #10;

        // --- PRUEBA 1: Acumular x = 5 (4 veces -> Total esperado: 20) ---
        x = 4'd5;
        start = 1;
        #10;
        start = 0; // Desactivar start tras el primer ciclo

        // Esperar a que complete el ciclo
        wait(done);
        #20;

        // --- PRUEBA 2: Acumular x = 3 (4 veces -> Total esperado: 12) ---
        x = 4'd3;
        start = 1;
        #10;
        start = 0;

        wait(done);
        #30;

        $display("Simulación completada con éxito.");
        $finish;
    end

endmodule

LAB00/src/accumulator.vcd
$date
	Sun Sep  6 11:53:21 2026
$end
$version
	Icarus Verilog
$end
$timescale
	1ps
$end
$scope module tb_accumulator $end
$var wire 1 ! done $end
$var wire 6 " acc [5:0] $end
$var reg 1 # clk $end
$var reg 1 $ rst $end
$var reg 1 % start $end
$var reg 4 & x [3:0] $end
$scope module uut $end
$var wire 1 # clk $end
$var wire 1 $ rst $end
$var wire 1 % start $end
$var wire 4 ' x [3:0] $end
$var parameter 2 ( S0_IDLE $end
$var parameter 2 ) S1_LOAD $end
$var parameter 2 * S2_ADD $end
$var parameter 2 + S3_DONE $end
$var reg 6 , acc [5:0] $end
$var reg 2 - cnt [1:0] $end
$var reg 1 ! done $end
$var reg 2 . next_state [1:0] $end
$var reg 2 / state [1:0] $end
$upscope $end
$upscope $end
$enddefinitions $end
$comment Show the parameter values. $end
$dumpall
b11 +
b10 *
b1 )
b0 (
$end
#0
$dumpvars
b0 /
b0 .
b0 -
b0 ,
b0 '
b0 &
0%
1$
0#
b0 "
0!
$end
#5000
1#
#10000
0#
#15000
1#
0$
#20000
0#
#25000
b1 /
b10 .
1#
1%
b101 &
b101 '
#30000
0#
#35000
b10 /
1#
0%
#40000
0#
#45000
b1 -
b101 "
b101 ,
1#
#50000
0#
#55000
b10 -
b1010 "
b1010 ,
1#
#60000
0#
#65000
b11 .
b11 -
b1111 "
b1111 ,
1#
#70000
0#
#75000
b0 .
b11 /
b0 -
b10100 "
b10100 ,
1#
#80000
0#
#85000
1!
b0 /
1#
#90000
0#
#95000
0!
1#
#100000
0#
#105000
b1 /
b10 .
1#
1%
b11 &
b11 '
#110000
0#
#115000
b10 /
b0 "
b0 ,
1#
0%
#120000
0#
#125000
b1 -
b11 "
b11 ,
1#
#130000
0#
#135000
b10 -
b110 "
b110 ,
1#
#140000
0#
#145000
b11 .
b11 -
b1001 "
b1001 ,
1#
#150000
0#
#155000
b0 .
b11 /
b0 -
b1100 "
b1100 ,
1#
#160000
0#
#165000
1!
b0 /
1#
#170000
0#
#175000
0!
1#
