LAB00/src/semaforo.v
module semaforo (
    input wire clk,
    input wire rst,
    output reg green,
    output reg yellow,
    output reg red
);

    // Codificación de los 3 estados
    localparam S0_GREEN  = 2'b00;
    localparam S1_YELLOW = 2'b01;
    localparam S2_RED    = 2'b10;

    reg [1:0] state, next_state;
    reg [2:0] count, next_count;

    // 1. Memoria/Registros (Lógica secuencial)
    always @(posedge clk or posedge rst) begin
        if (rst) begin
            state <= S0_GREEN;
            count <= 3'd0;
        end else begin
            state <= next_state;
            count <= next_count;
        end
    end

    // 2. Transiciones de estado (Lógica combinacional)
    always @(*) begin
        next_state = state;
        next_count = count + 1'b1;

        case (state)
            S0_GREEN: begin
                if (count == 3'd4) begin // 5 ciclos (0 a 4)
                    next_state = S1_YELLOW;
                    next_count = 3'd0;
                end
            end
            S1_YELLOW: begin
                if (count == 3'd1) begin // 2 ciclos (0 a 1)
                    next_state = S2_RED;
                    next_count = 3'd0;
                end
            end
            S2_RED: begin
                if (count == 3'd3) begin // 4 ciclos (0 a 3)
                    next_state = S0_GREEN;
                    next_count = 3'd0;
                end
            end
            default: begin
                next_state = S0_GREEN;
                next_count = 3'd0;
            end
        endcase
    end

    // 3. Salidas tipo Moore
    always @(*) begin
        green  = (state == S0_GREEN);
        yellow = (state == S1_YELLOW);
        red    = (state == S2_RED);
    end

endmodule

src/tb_semaforo.v
`timescale 1ns/1ps

module tb_semaforo;

    reg clk;
    reg rst;
    wire green;
    wire yellow;
    wire red;

    // Instancia del módulo
    semaforo uut (
        .clk(clk),
        .rst(rst),
        .green(green),
        .yellow(yellow),
        .red(red)
    );

    // Generador de reloj (10ns de período)
    always #5 clk = ~clk;

    initial begin
        // Instrucciones para guardar las señales para GTKWave
        $dumpfile("semaforo.vcd");
        $dumpvars(0, tb_semaforo);

        // Estado inicial
        clk = 0;
        rst = 1;

        // Liberar reset a los 20ns
        #20 rst = 0;

        // Correr la simulación por 200ns
        #200;

        $finish;
    end

endmodule

LAB00/src/semaforo.vcd
$date
	Sun Sep  6 10:57:21 2026
$end
$version
	Icarus Verilog
$end
$timescale
	1ps
$end
$scope module tb_semaforo $end
$var wire 1 ! yellow $end
$var wire 1 " red $end
$var wire 1 # green $end
$var reg 1 $ clk $end
$var reg 1 % rst $end
$scope module uut $end
$var wire 1 $ clk $end
$var wire 1 % rst $end
$var parameter 2 & S0_GREEN $end
$var parameter 2 ' S1_YELLOW $end
$var parameter 2 ( S2_RED $end
$var reg 3 ) count [2:0] $end
$var reg 1 # green $end
$var reg 3 * next_count [2:0] $end
$var reg 2 + next_state [1:0] $end
$var reg 1 " red $end
$var reg 2 , state [1:0] $end
$var reg 1 ! yellow $end
$upscope $end
$upscope $end
$enddefinitions $end
$comment Show the parameter values. $end
$dumpall
b10 (
b1 '
b0 &
$end
#0
$dumpvars
b0 ,
b0 +
b1 *
b0 )
1%
0$
1#
0"
0!
$end
#5000
1$
#10000
0$
#15000
1$
#20000
0$
0%
#25000
b10 *
b1 )
1$
#30000
0$
#35000
b11 *
b10 )
1$
#40000
0$
#45000
b100 *
b11 )
1$
#50000
0$
#55000
b1 +
b0 *
b100 )
1$
#60000
0$
#65000
1!
0#
b1 *
b0 )
b1 ,
1$
#70000
0$
#75000
b10 +
b0 *
b1 )
1$
#80000
0$
#85000
1"
0!
b1 *
b0 )
b10 ,
1$
#90000
0$
#95000
b10 *
b1 )
1$
#100000
0$
#105000
b11 *
b10 )
1$
#110000
0$
#115000
b0 +
b0 *
b11 )
1$
#120000
0$
#125000
0"
1#
b1 *
b0 )
b0 ,
1$
#130000
0$
#135000
b10 *
b1 )
1$
#140000
0$
#145000
b11 *
b10 )
1$
#150000
0$
#155000
b100 *
b11 )
1$
#160000
0$
#165000
b1 +
b0 *
b100 )
1$
#170000
0$
#175000
1!
0#
b1 *
b0 )
b1 ,
1$
#180000
0$
#185000
b10 +
b0 *
b1 )
1$
#190000
0$
#195000
1"
0!
b1 *
b0 )
b10 ,
1$
#200000
0$
#205000
b10 *
b1 )
1$
#210000
0$
#215000
b11 *
b10 )
1$
