src/serial_tx.v
module serial_tx #(
    parameter CLKS_PER_BIT = 8
)(
    input wire clk,
    input wire rst,
    input wire start,
    input wire [7:0] data_in,
    output reg tx,
    output reg busy,
    output reg done
);

    // Definición de Estados de la FSM
    localparam S0_IDLE       = 3'b000;
    localparam S1_LOAD       = 3'b001;
    localparam S2_BIT_HOLD   = 3'b010;
    localparam S3_SHIFT_NEXT = 3'b011;
    localparam S4_DONE       = 3'b100;

    reg [2:0] state, next_state;
    reg [7:0] shift_reg;
    reg [2:0] bit_cnt;
    reg [$clog2(CLKS_PER_BIT)-1:0] tick_cnt;

    // 1. Registro de Estado (Lógica Secuencial)
    always @(posedge clk or posedge rst) begin
        if (rst) begin
            state <= S0_IDLE;
        end else begin
            state <= next_state;
        end
    end

    // 2. Lógica del Próximo Estado (Lógica Combinacional)
    always @(*) begin
        case (state)
            S0_IDLE:       next_state = (start) ? S1_LOAD : S0_IDLE;
            S1_LOAD:       next_state = S2_BIT_HOLD;
            S2_BIT_HOLD:   next_state = (tick_cnt == CLKS_PER_BIT - 1) ? S3_SHIFT_NEXT : S2_BIT_HOLD;
            S3_SHIFT_NEXT: next_state = (bit_cnt == 3'd7) ? S4_DONE : S2_BIT_HOLD;
            S4_DONE:       next_state = S0_IDLE;
            default:       next_state = S0_IDLE;
        endcase
    end

    // 3. Datapath y Salidas (Lógica Secuencial)
    always @(posedge clk or posedge rst) begin
        if (rst) begin
            shift_reg <= 8'h00;
            bit_cnt   <= 3'd0;
            tick_cnt  <= 0;
            tx        <= 1'b1;
            busy      <= 1'b0;
            done      <= 1'b0;
        end else begin
            case (state)
                S0_IDLE: begin
                    tx   <= 1'b1;
                    busy <= 1'b0;
                    done <= 1'b0;
                end

                S1_LOAD: begin
                    shift_reg <= data_in;
                    bit_cnt   <= 3'd0;
                    tick_cnt  <= 0;
                    busy      <= 1'b1;
                    tx        <= 1'b1;
                    done      <= 1'b0;
                end

                S2_BIT_HOLD: begin
                    tx   <= shift_reg[0];
                    busy <= 1'b1;
                    done <= 1'b0;
                    if (tick_cnt < CLKS_PER_BIT - 1) begin
                        tick_cnt <= tick_cnt + 1'b1;
                    end
                end

                S3_SHIFT_NEXT: begin
                    tx        <= shift_reg[0];
                    busy      <= 1'b1;
                    done      <= 1'b0;
                    shift_reg <= shift_reg >> 1;
                    bit_cnt   <= bit_cnt + 3'd1;
                    tick_cnt  <= 0;
                end

                S4_DONE: begin
                    tx   <= 1'b1;
                    busy <= 1'b0;
                    done <= 1'b1;
                end
            endcase
        end
    end

endmodule

src/tb_serial_tx.v
`timescale 1ns/1ps

module tb_serial_tx;

    parameter CLKS_PER_BIT = 8;

    // Entradas del UUT (reg)
    reg clk;
    reg rst;
    reg start;
    reg [7:0] data_in;

    // Salidas del UUT (wire)
    wire tx;
    wire busy;
    wire done;

    // Instancia del transmisor
    serial_tx #(
        .CLKS_PER_BIT(CLKS_PER_BIT)
    ) uut (
        .clk(clk),
        .rst(rst),
        .start(start),
        .data_in(data_in),
        .tx(tx),
        .busy(busy),
        .done(done)
    );

    // Generador de Reloj (Periodo = 10ns)
    always #5 clk = ~clk;

    initial begin
        // Archivo de ondas para GTKWave
        $dumpfile("wave.vcd");
        $dumpvars(0, tb_serial_tx);

        // Inicialización
        clk = 0;
        rst = 1;
        start = 0;
        data_in = 8'h00;

        // Reset inicial
        #20;
        rst = 0;
        #20;

        // --- PRUEBA 1: Transmitir 8'hA5 (10100101b) ---
        data_in = 8'hA5;
        start = 1;
        #10;          // Pulso de start de exactamente 1 ciclo
        start = 0;

        wait(done);
        #30;

        // --- PRUEBA 2: Transmitir 8'h3C (00111100b) ---
        data_in = 8'h3C;
        start = 1;
        #10;          // Pulso de start de exactamente 1 ciclo
        start = 0;

        wait(done);
        #50;

        $display("Simulación completada exitosamente.");
        $finish;
    end

endmodule

LAB00/src/wave.vcd
$date
	Sun Sep  6 12:38:51 2026
$end
$version
	Icarus Verilog
$end
$timescale
	1ps
$end
$scope module tb_serial_tx $end
$var wire 1 ! tx $end
$var wire 1 " done $end
$var wire 1 # busy $end
$var parameter 32 $ CLKS_PER_BIT $end
$var reg 1 % clk $end
$var reg 8 & data_in [7:0] $end
$var reg 1 ' rst $end
$var reg 1 ( start $end
$scope module uut $end
$var wire 1 % clk $end
$var wire 8 ) data_in [7:0] $end
$var wire 1 ' rst $end
$var wire 1 ( start $end
$var parameter 32 * CLKS_PER_BIT $end
$var parameter 3 + S0_IDLE $end
$var parameter 3 , S1_LOAD $end
$var parameter 3 - S2_BIT_HOLD $end
$var parameter 3 . S3_SHIFT_NEXT $end
$var parameter 3 / S4_DONE $end
$var reg 3 0 bit_cnt [2:0] $end
$var reg 1 # busy $end
$var reg 1 " done $end
$var reg 3 1 next_state [2:0] $end
$var reg 8 2 shift_reg [7:0] $end
$var reg 3 3 state [2:0] $end
$var reg 3 4 tick_cnt [2:0] $end
$var reg 1 ! tx $end
$upscope $end
$upscope $end
$enddefinitions $end
$comment Show the parameter values. $end
$dumpall
b100 /
b11 .
b10 -
b1 ,
b0 +
b1000 *
b1000 $
$end
#0
$dumpvars
b0 4
b0 3
b0 2
b0 1
b0 0
b0 )
0(
1'
b0 &
0%
0#
0"
1!
$end
#5000
1%
#10000
0%
#15000
1%
#20000
0%
0'
#25000
1%
#30000
0%
#35000
1%
#40000
b1 1
0%
1(
b10100101 &
b10100101 )
#45000
b10 1
b1 3
1%
#50000
0%
0(
#55000
b10 3
1#
b10100101 2
1%
#60000
0%
#65000
b1 4
1%
#70000
0%
#75000
b10 4
1%
#80000
0%
#85000
b11 4
1%
#90000
0%
#95000
b100 4
1%
#100000
0%
#105000
b101 4
1%
#110000
0%
#115000
b110 4
1%
#120000
0%
#125000
b11 1
b111 4
1%
#130000
0%
#135000
b10 1
b11 3
1%
#140000
0%
#145000
b0 4
b1 0
b1010010 2
b10 3
1%
#150000
0%
#155000
b1 4
0!
1%
#160000
0%
#165000
b10 4
1%
#170000
0%
#175000
b11 4
1%
#180000
0%
#185000
b100 4
1%
#190000
0%
#195000
b101 4
1%
#200000
0%
#205000
b110 4
1%
#210000
0%
#215000
b11 1
b111 4
1%
#220000
0%
#225000
b10 1
b11 3
1%
#230000
0%
#235000
b10 3
b0 4
b10 0
b101001 2
1%
#240000
0%
#245000
b1 4
1!
1%
#250000
0%
#255000
b10 4
1%
#260000
0%
#265000
b11 4
1%
#270000
0%
#275000
b100 4
1%
#280000
0%
#285000
b101 4
1%
#290000
0%
#295000
b110 4
1%
#300000
0%
#305000
b11 1
b111 4
1%
#310000
0%
#315000
b10 1
b11 3
1%
#320000
0%
#325000
b0 4
b11 0
b10100 2
b10 3
1%
#330000
0%
#335000
b1 4
0!
1%
#340000
0%
#345000
b10 4
1%
#350000
0%
#355000
b11 4
1%
#360000
0%
#365000
b100 4
1%
#370000
0%
#375000
b101 4
1%
#380000
0%
#385000
b110 4
1%
#390000
0%
#395000
b11 1
b111 4
1%
#400000
0%
#405000
b10 1
b11 3
1%
#410000
0%
#415000
b10 3
b0 4
b100 0
b1010 2
1%
#420000
0%
#425000
b1 4
1%
#430000
0%
#435000
b10 4
1%
#440000
0%
#445000
b11 4
1%
#450000
0%
#455000
b100 4
1%
#460000
0%
#465000
b101 4
1%
#470000
0%
#475000
b110 4
1%
#480000
0%
#485000
b11 1
b111 4
1%
#490000
0%
#495000
b10 1
b11 3
1%
#500000
0%
#505000
b0 4
b101 0
b101 2
b10 3
1%
#510000
0%
#515000
b1 4
1!
1%
#520000
0%
#525000
b10 4
1%
#530000
0%
#535000
b11 4
1%
#540000
0%
#545000
b100 4
1%
#550000
0%
#555000
b101 4
1%
#560000
0%
#565000
b110 4
1%
#570000
0%
#575000
b11 1
b111 4
1%
#580000
0%
#585000
b10 1
b11 3
1%
#590000
0%
#595000
b10 3
b0 4
b110 0
b10 2
1%
#600000
0%
#605000
b1 4
0!
1%
#610000
0%
#615000
b10 4
1%
#620000
0%
#625000
b11 4
1%
#630000
0%
#635000
b100 4
1%
#640000
0%
#645000
b101 4
1%
#650000
0%
#655000
b110 4
1%
#660000
0%
#665000
b11 1
b111 4
1%
#670000
0%
#675000
b10 1
b11 3
1%
#680000
0%
#685000
b0 4
b111 0
b1 2
b10 3
1%
#690000
0%
#695000
b1 4
1!
1%
#700000
0%
#705000
b10 4
1%
#710000
0%
#715000
b11 4
1%
#720000
0%
#725000
b100 4
1%
#730000
0%
#735000
b101 4
1%
#740000
0%
#745000
b110 4
1%
#750000
0%
#755000
b11 1
b111 4
1%
#760000
0%
#765000
b100 1
b11 3
1%
#770000
0%
#775000
b0 1
b100 3
b0 4
b0 0
b0 2
1%
#780000
0%
#785000
1"
0#
b0 3
1%
#790000
0%
#795000
0"
1%
#800000
0%
#805000
1%
#810000
0%
#815000
b1 3
b10 1
1%
1(
b111100 &
b111100 )
#820000
0%
#825000
1#
b111100 2
b10 3
1%
0(
#830000
0%
#835000
b1 4
0!
1%
#840000
0%
#845000
b10 4
1%
#850000
0%
#855000
b11 4
1%
#860000
0%
#865000
b100 4
1%
#870000
0%
#875000
b101 4
1%
#880000
0%
#885000
b110 4
1%
#890000
0%
#895000
b11 1
b111 4
1%
#900000
0%
#905000
b10 1
b11 3
1%
#910000
0%
#915000
b10 3
b0 4
b1 0
b11110 2
1%
#920000
0%
#925000
b1 4
1%
#930000
0%
#935000
b10 4
1%
#940000
0%
#945000
b11 4
1%
#950000
0%
#955000
b100 4
1%
#960000
0%
#965000
b101 4
1%
#970000
0%
#975000
b110 4
1%
#980000
0%
#985000
b11 1
b111 4
1%
#990000
0%
#995000
b10 1
b11 3
1%
#1000000
0%
#1005000
b0 4
b10 0
b1111 2
b10 3
1%
#1010000
0%
#1015000
b1 4
1!
1%
#1020000
0%
#1025000
b10 4
1%
#1030000
0%
#1035000
b11 4
1%
#1040000
0%
#1045000
b100 4
1%
#1050000
0%
#1055000
b101 4
1%
#1060000
0%
#1065000
b110 4
1%
#1070000
0%
#1075000
b11 1
b111 4
1%
#1080000
0%
#1085000
b10 1
b11 3
1%
#1090000
0%
#1095000
b10 3
b0 4
b11 0
b111 2
1%
#1100000
0%
#1105000
b1 4
1%
#1110000
0%
#1115000
b10 4
1%
#1120000
0%
#1125000
b11 4
1%
#1130000
0%
#1135000
b100 4
1%
#1140000
0%
#1145000
b101 4
1%
#1150000
0%
#1155000
b110 4
1%
#1160000
0%
#1165000
b11 1
b111 4
1%
#1170000
0%
#1175000
b10 1
b11 3
1%
#1180000
0%
#1185000
b0 4
b100 0
b11 2
b10 3
1%
#1190000
0%
#1195000
b1 4
1%
#1200000
0%
#1205000
b10 4
1%
#1210000
0%
#1215000
b11 4
1%
#1220000
0%
#1225000
b100 4
1%
#1230000
0%
#1235000
b101 4
1%
#1240000
0%
#1245000
b110 4
1%
#1250000
0%
#1255000
b11 1
b111 4
1%
#1260000
0%
#1265000
b10 1
b11 3
1%
#1270000
0%
#1275000
b10 3
b0 4
b101 0
b1 2
1%
#1280000
0%
#1285000
b1 4
1%
#1290000
0%
#1295000
b10 4
1%
#1300000
0%
#1305000
b11 4
1%
#1310000
0%
#1315000
b100 4
1%
#1320000
0%
#1325000
b101 4
1%
#1330000
0%
#1335000
b110 4
1%
#1340000
0%
#1345000
b11 1
b111 4
1%
#1350000
0%
#1355000
b10 1
b11 3
1%
#1360000
0%
#1365000
b0 4
b110 0
b0 2
b10 3
1%
#1370000
0%
#1375000
b1 4
0!
1%
#1380000
0%
#1385000
b10 4
1%
#1390000
0%
#1395000
b11 4
1%
#1400000
0%
#1405000
b100 4
1%
#1410000
0%
#1415000
b101 4
1%
#1420000
0%
#1425000
b110 4
1%
#1430000
0%
#1435000
b11 1
b111 4
1%
#1440000
0%
#1445000
b10 1
b11 3
1%
#1450000
0%
#1455000
b10 3
b0 4
b111 0
1%
#1460000
0%
#1465000
b1 4
1%
#1470000
0%
#1475000
b10 4
1%
#1480000
0%
#1485000
b11 4
1%
#1490000
0%
#1495000
b100 4
1%
#1500000
0%
#1505000
b101 4
1%
#1510000
0%
#1515000
b110 4
1%
#1520000
0%
#1525000
b11 1
b111 4
1%
#1530000
0%
#1535000
b100 1
b11 3
1%
#1540000
0%
#1545000
b0 1
b0 4
b0 0
b100 3
1%
#1550000
0%
#1555000
b0 3
1"
0#
1!
1%
#1560000
0%
#1565000
0"
1%
